configureout.py
configureout-2.3.dist-info/licenses/LICENSE
configureout-2.3.dist-info/METADATA
configureout-2.3.dist-info/WHEEL
configureout-2.3.dist-info/top_level.txt
configureout-2.3.dist-info/RECORD
