Metadata-Version: 2.4
Name: configureout
Version: 2.3
Summary: A lightweight and flexible configuration loader for Python.
Author-email: EightShift <the8shift@gmail.com>
License: MIT
Project-URL: Homepage, https://github.com/EightShift/configureout
Keywords: configuration,loader
Classifier: Programming Language :: Python :: 3
Classifier: License :: OSI Approved :: MIT License
Classifier: Operating System :: OS Independent
Requires-Python: >=3.9
License-File: LICENSE
Dynamic: license-file
